authbroker_client/__init__.py
authbroker_client/apps.py
authbroker_client/backends.py
authbroker_client/logging.py
authbroker_client/middleware.py
authbroker_client/urls.py
authbroker_client/utils.py
authbroker_client/version.py
authbroker_client/views.py
tests/__init__.py
tests/conftest.py
tests/settings.py
tests/test_backends.py
tests/test_logging.py
tests/test_middleware.py
tests/test_urls.py
tests/test_utils.py
tests/test_version.py
tests/test_views.py
tests/urls.py
django_staff_sso_client-5.1.0.dist-info/METADATA
django_staff_sso_client-5.1.0.dist-info/WHEEL
django_staff_sso_client-5.1.0.dist-info/top_level.txt
django_staff_sso_client-5.1.0.dist-info/RECORD
