Metadata-Version: 2.4
Name: django_staff_sso_client
Version: 5.1.0
Summary: Reusable Django app to facilitate gov.uk Staff Single Sign On
Home-page: https://github.com/uktrade/django-staff-sso-client/
Author: Department for International Trade
License: MIT
Classifier: Environment :: Web Environment
Classifier: Framework :: Django
Classifier: Intended Audience :: Developers
Classifier: Operating System :: OS Independent
Classifier: Programming Language :: Python
Classifier: Programming Language :: Python :: 3.9
Classifier: Programming Language :: Python :: 3.13
Classifier: Programming Language :: Python :: Implementation :: PyPy
Classifier: Framework :: Django
Classifier: Framework :: Django :: 4.2
Classifier: Framework :: Django :: 5.0
Classifier: Framework :: Django :: 5.1
Classifier: Framework :: Django :: 5.2
Classifier: Topic :: Software Development :: Libraries :: Python Modules
Requires-Dist: Django<6.0,>=4.2.10
Requires-Dist: requests_oauthlib
Requires-Dist: django-log-formatter-asim~=1.1
Provides-Extra: test
Requires-Dist: pytest==7.4.4; extra == "test"
Requires-Dist: pytest-cov; extra == "test"
Requires-Dist: pytest-django; extra == "test"
Requires-Dist: flake8==5.0.4; extra == "test"
Requires-Dist: requests_mock; extra == "test"
Requires-Dist: codecov; extra == "test"
Requires-Dist: build; extra == "test"
Requires-Dist: twine; extra == "test"
Requires-Dist: wheel; extra == "test"
Requires-Dist: setuptools; extra == "test"
Requires-Dist: requests-mock; extra == "test"
Requires-Dist: raven; extra == "test"
Dynamic: author
Dynamic: classifier
Dynamic: description
Dynamic: description-content-type
Dynamic: home-page
Dynamic: license
Dynamic: provides-extra
Dynamic: requires-dist
Dynamic: summary
